README.md
setup.py
lpmp_gm/__init__.py
lpmp_gm/raw_solvers.py
lpmp_ldp/__init__.py
lpmp_ldp/raw_solvers.py
lpmp_mc/__init__.py
lpmp_mc/multicut.py
lpmp_mc/raw_solvers.py
lpmp_mc/utils.py
lpmp_py.egg-info/PKG-INFO
lpmp_py.egg-info/SOURCES.txt
lpmp_py.egg-info/dependency_links.txt
lpmp_py.egg-info/not-zip-safe
lpmp_py.egg-info/top_level.txt